fsm-assignment/problem1_seqdet/seq_detect_mealy.v
`timescale 1ns / 1ns

module seq_detect_mealy(
    input wire clk,
    input wire rst,
    input wire din,
    output reg y
);

    
    parameter S0 = 2'b00; 
    parameter S1 = 2'b01; 
    parameter S2 = 2'b10; 
    parameter S3 = 2'b11; 

    // State register
    reg [1:0] current_state, next_state;

    //positive egde logic
    always @(posedge clk) 
    begin
        if (rst) 
        begin
            current_state <= S0;
        end 
        else 
        begin
            current_state <= next_state;
        end
    end

    // State transition
    always @(*) 
    begin
        next_state = current_state;

        case (current_state)
            S0: 
            begin
                if (din == 1'b1) next_state = S1;
                else next_state = S0;
                y = 1'b0;
            end
            S1: 
            begin
                if (din == 1'b1) next_state = S2;
                else next_state = S0;
                y = 1'b0;
            end
            S2: 
            begin
                if (din == 1'b0) next_state = S3;
                else next_state = S2; 
                y = 1'b0;
            end
            S3: 
            begin
                if (din == 1'b1) begin
                    next_state = S2; 
                    y = 1'b1;
                end else begin
                    next_state = S0;
                end
            end
            default: next_state = S0;
        endcase
    end

endmodule

fsm-assignment/problem1_seqdet/tb_seq_detect_mealy.v
`timescale 1ns/1ns
`include "seq_detect_mealy.v"

module tb_seq_detect_mealy;

reg clk;
reg rst;
reg din;
wire y;

seq_detect_mealy dut(
   .clk(clk),
   .rst(rst),
   .din(din),
   .y(y) 
);

always #5 clk = ~clk;

initial begin
        clk = 0;
    end

initial begin 
    $dumpfile("seq_detect_mealy.vcd");
    $dumpvars(0, dut);

    rst = 1;
    clk = 0;
    din = 0;
    #10;
    rst = 0;

    $display("Test Start.....");

    //seq 1 : 1101
   
    #10 din = 1;
    #10 din = 1;
    #10 din = 0;
    #10 din = 1;

    //Seq 2: 111101 (overlapping)
    #10 din = 1;
    #10 din = 1;
    #10 din = 1;
    #10 din = 1;
    #10 din = 0;
    #10 din = 1;

    // Seq 3: 11011011101 (overlaps)
        #10 din = 1;
        #10 din = 1;
        #10 din = 0;
        #10 din = 1;
        #10 din = 1;
        #10 din = 0;
        #10 din = 1;
        #10 din = 1;
        #10 din = 1;
        #10 din = 0;
        #10 din = 1;
     #20
     $display("Test_Completed....");  
     $finish;
end
endmodule

fsm-assignment/problem1_seqdet/wave/seq_detect_mealy.vcd
$date
	Tue Aug 19 12:11:59 2025
$end
$version
	Icarus Verilog
$end
$timescale
	1ns
$end
$scope module tb_seq_detect_mealy $end
$scope module dut $end
$var wire 1 ! clk $end
$var wire 1 " din $end
$var wire 1 # rst $end
$var reg 2 $ current_state [1:0] $end
$var reg 2 % next_state [1:0] $end
$var reg 1 & y $end
$upscope $end
$upscope $end
$enddefinitions $end
#0
$dumpvars
x&
b0 %
bx $
1#
0"
0!
$end
#5
0&
b0 $
1!
#10
0!
0#
#15
1!
#20
b1 %
0!
1"
#25
b10 %
b1 $
1!
#30
0!
#35
b10 $
1!
#40
b11 %
0!
0"
#45
b0 %
b11 $
1!
#50
1&
b10 %
0!
1"
#55
0&
b10 $
1!
#60
0!
#65
1!
#70
0!
#75
1!
#80
0!
#85
1!
#90
0!
#95
1!
#100
b11 %
0!
0"
#105
b0 %
b11 $
1!
#110
1&
b10 %
0!
1"
#115
0&
b10 $
1!
#120
0!
#125
1!
#130
0!
#135
1!
#140
b11 %
0!
0"
#145
b0 %
b11 $
1!
#150
1&
b10 %
0!
1"
#155
0&
b10 $
1!
#160
0!
#165
1!
#170
b11 %
0!
0"
#175
b0 %
b11 $
1!
#180
1&
b10 %
0!
1"
#185
0&
b10 $
1!
#190
0!
#195
1!
#200
0!
#205
1!
#210
b11 %
0!
0"
#215
b0 %
b11 $
1!
#220
1&
b10 %
0!
1"
#225
0&
b10 $
1!
