fsm-assignment/problem3_vending/vending_mealy.v
`timescale 1ns / 1ns

module vending_mealy (
    input wire clk,
    input wire rst,
    input wire [1:0] coin,  
    output reg dispense,    
    output reg chg5         
);

    
    parameter S0 = 2'b00;  
    parameter S5 = 2'b01;  // 5 rs
    parameter S10 = 2'b10; // 10 rs
    parameter S15 = 2'b11; // 15 rs
    
    
    reg [1:0] current_state, next_state;

     always @(posedge clk) begin
        if (rst) begin
            current_state <= S0;
        end else begin
            current_state <= next_state;
        end
    end

    
    always @(*) begin
        next_state = current_state;
        dispense = 1'b0;
        chg5 = 1'b0;

        case (current_state)
            S0: begin
                if (coin == 2'b01) next_state = S5;
                else if (coin == 2'b10) next_state = S10;
                else next_state = S0;
            end
            S5: begin
                if (coin == 2'b01) next_state = S10;
                else if (coin == 2'b10) next_state = S15;
                else next_state = S5;
            end
            S10: begin
                if (coin == 2'b01) next_state = S15;
                else if (coin == 2'b10) begin
                    next_state = S0;
                    dispense = 1'b1;
                end else next_state = S10;
            end
            S15: begin
                if (coin == 2'b01) begin
                    next_state = S0;
                    dispense = 1'b1;
                end else if (coin == 2'b10) begin
                    next_state = S0;
                    dispense = 1'b1;
                    chg5 = 1'b1;
                end else next_state = S15;
            end
            default: next_state = S0;
        endcase
    end

endmodule

fsm-assignment/problem3_vending/tb_vending_mealy.v
`timescale 1ns / 1ns
`include"vending_mealy.v"

module tb_vending_mealy;

    reg clk;
    reg rst;
    reg [1:0] coin;
    wire dispense;
    wire chg5;

    vending_mealy dut (
        .clk(clk),
        .rst(rst),
        .coin(coin),
        .dispense(dispense),
        .chg5(chg5)
    );

    
    always #5 clk = ~clk;

    initial begin
        
        $dumpfile("vending_mealy.vcd");
        $dumpvars(0, tb_vending_mealy);
        
        
        clk = 0;
        rst = 1;
        coin = 2'b00;
        #10;
        rst = 0;
        

        // Test 1:
        $display("Test 1: Insert 4 x 5 cents (no change)");
        #10 coin = 2'b01; // S0 -> S5
        #10 coin = 2'b00;
        #10 coin = 2'b01; // S5 -> S10
        #10 coin = 2'b00;
        #10 coin = 2'b01; // S10 -> S15
        #10 coin = 2'b00;
        #10 coin = 2'b01; // S15 -> S0, dispense=1
        #10 coin = 2'b00;

        // Test 2:
        $display("\nTest 2: Insert 2 x 10 cents");
        #10 coin = 2'b10; // S0 -> S10
        #10 coin = 2'b00;
        #10 coin = 2'b10; // S10 -> S0, dispense=1, 
        #10 coin = 2'b00;

        // Test 3:
        $display("\nTest 3: Insert 5, 10, 10 cents (with change)");
        #10 coin = 2'b01; // S0 -> S5
        #10 coin = 2'b00;
        #10 coin = 2'b10; // S5 -> S10
        #10 coin = 2'b00;
        #10 coin = 2'b10; // S10-> S0, dispense=1, chg5=1
        #10 coin = 2'b00;
        
        #20 $finish;
    end
endmodule

fsm-assignment/problem3_vending/wave/vending_mealy.vcd
$date
	Tue Aug 19 22:31:36 2025
$end
$version
	Icarus Verilog
$end
$timescale
	1ns
$end
$scope module tb_vending_mealy $end
$var wire 1 ! chg5 $end
$var wire 1 " dispense $end
$var reg 1 # clk $end
$var reg 2 $ coin [1:0] $end
$var reg 1 % rst $end
$scope module dut $end
$var wire 1 & clk $end
$var wire 2 ' coin [1:0] $end
$var wire 1 ( rst $end
$var reg 1 ) chg5 $end
$var reg 2 * current_state [1:0] $end
$var reg 1 + dispense $end
$var reg 2 , next_state [1:0] $end
$upscope $end
$upscope $end
$enddefinitions $end
#0
$dumpvars
b0 ,
0+
bx *
0)
1(
b0 '
0&
1%
b0 $
0#
0"
0!
$end
#5
b0 *
1#
1&
#10
0#
0&
0%
0(
#15
1#
1&
#20
b1 ,
0#
0&
b1 $
b1 '
#25
b10 ,
b1 *
1#
1&
#30
b1 ,
0#
0&
b0 $
b0 '
#35
1#
1&
#40
b10 ,
0#
0&
b1 $
b1 '
#45
b11 ,
b10 *
1#
1&
#50
b10 ,
0#
0&
b0 $
b0 '
#55
1#
1&
#60
b11 ,
0#
0&
b1 $
b1 '
#65
1+
1"
b0 ,
b11 *
1#
1&
#70
0+
0"
b11 ,
0#
0&
b0 $
b0 '
#75
1#
1&
#80
1+
1"
b0 ,
0#
0&
b1 $
b1 '
#85
b1 ,
0+
0"
b0 *
1#
1&
#90
b0 ,
0#
0&
b0 $
b0 '
#95
1#
1&
#100
b10 ,
0#
0&
b10 $
b10 '
#105
1+
1"
b0 ,
b10 *
1#
1&
#110
0+
0"
b10 ,
0#
0&
b0 $
b0 '
#115
1#
1&
#120
1+
1"
b0 ,
0#
0&
b10 $
b10 '
#125
b10 ,
0+
0"
b0 *
1#
1&
#130
b0 ,
0#
0&
b0 $
b0 '
#135
1#
1&
#140
b1 ,
0#
0&
b1 $
b1 '
#145
b10 ,
b1 *
1#
1&
#150
b1 ,
0#
0&
b0 $
b0 '
#155
1#
1&
#160
b11 ,
0#
0&
b10 $
b10 '
#165
1)
1!
1+
1"
b0 ,
b11 *
1#
1&
#170
0)
0!
0+
0"
b11 ,
0#
0&
b0 $
b0 '
#175
1#
1&
#180
1)
1!
1+
1"
b0 ,
0#
0&
b10 $
b10 '
#185
b10 ,
0)
0!
0+
0"
b0 *
1#
1&
#190
b0 ,
0#
0&
b0 $
b0 '
