fsm-assignment/ problem2_traffic/ problem2_traffic/traffic_light.v
`timescale 1ns / 1ns

module traffic_light (
    input wire clk,
    input wire rst,
    input wire tick,
    
    output wire ns_g, ns_y, ns_r,
    
    output wire ew_g, ew_y, ew_r

);

    // State encoding for the Moore FSM
    parameter NS_GREEN = 2'b00;
    parameter NS_YELLOW = 2'b01;
    parameter EW_GREEN = 2'b10;
    parameter EW_YELLOW = 2'b11;

    // State register
    reg [1:0] current_state, next_state;
    
    // Per-phase tick counter
    reg [2:0] tick_count;
    parameter G_DUR = 3'd5; // 5 ticks for green
    parameter Y_DUR = 3'd2; // 2 ticks for yellow

    // Synchronous state transition logic with active-high reset
    always @(posedge clk) begin
        if (rst) 
        begin
            current_state <= NS_GREEN;
            tick_count <= 0;
        end 
        else 
        begin
            current_state <= next_state;
            if (tick) 
            begin
                tick_count <= tick_count + 1;
            end
        end
    end

    // Combinational next-state logic
    always @(*) begin
        next_state = current_state;
        case (current_state)
            NS_GREEN: 
            begin
                if (tick && tick_count == G_DUR - 1) next_state = NS_YELLOW;
            end
            NS_YELLOW: 
            begin
                if (tick && tick_count == Y_DUR - 1) next_state = EW_GREEN;
            end
            EW_GREEN: 
            begin
                if (tick && tick_count == G_DUR - 1) next_state = EW_YELLOW;
            end
            EW_YELLOW: 
            begin
                if (tick && tick_count == Y_DUR - 1) next_state = NS_GREEN;
            end
        endcase
    end
    
    // Combinational output logic (Moore FSM)
    assign ns_g = (current_state == NS_GREEN);
    assign ns_y = (current_state == NS_YELLOW);
    assign ns_r = (current_state == EW_GREEN || current_state == EW_YELLOW);
    assign ew_g = (current_state == EW_GREEN);
    assign ew_y = (current_state == EW_YELLOW);
    assign ew_r = (current_state == NS_GREEN || current_state == NS_YELLOW);
    

endmodule

fsm-assignment/ problem2_traffic/tb_traffic_light.v
// tb_traffic_light.v
`timescale 1ns / 1ns
`include "traffic_light.v"

module tb_traffic_light;

    reg clk;
    reg rst;
    reg tick;
    wire ns_g, ns_y, ns_r;
    wire ew_g, ew_y, ew_r;
    
    parameter CLK_PERIOD = 10; 
    parameter TICK_PERIOD = 1_000; // 1 second for 1 Hz tick

    // Instantiate the DUT
    traffic_light dut (
        .clk(clk),
        .rst(rst),
        .tick(tick),
        .ns_g(ns_g),
        .ns_y(ns_y),
        .ns_r(ns_r),
        .ew_g(ew_g),
        .ew_y(ew_y),
        .ew_r(ew_r)
    );

    // Clock and tick generation
    always #(CLK_PERIOD / 2) clk = ~clk;

    initial begin
        clk = 0;
        rst = 1;
        tick = 0;
        #20; // Hold reset
        rst = 0;
        
        // Generate a 1 Hz tick pulse
        forever begin
            #((TICK_PERIOD / 2));
            tick = 1;
            #((TICK_PERIOD / 2));
            tick = 0;
        end
    end
    
    // Waveform dumping and simulation control
    initial begin
        $dumpfile("traffic_light.vcd");
        $dumpvars(0, tb_traffic_light);
        
        $display("Test Started...");
        
        // Run the simulation for a few cycles
        #(TICK_PERIOD * 15); // Simulate for 15 seconds
        
        $display("Test Completed.");
        $finish;
    end

endmodule

fsm-assignment/ problem2_traffic/wave/traffic_light.vcd
$date
	Tue Aug 19 15:04:55 2025
$end
$version
	Icarus Verilog
$end
$timescale
	1ns
$end
$scope module tb_traffic_light $end
$var wire 1 ! ew_g $end
$var wire 1 " ew_r $end
$var wire 1 # ew_y $end
$var wire 1 $ ns_g $end
$var wire 1 % ns_r $end
$var wire 1 & ns_y $end
$var reg 1 ' clk $end
$var reg 1 ( rst $end
$var reg 1 ) tick $end
$scope module dut $end
$var wire 1 * clk $end
$var wire 1 ! ew_g $end
$var wire 1 " ew_r $end
$var wire 1 # ew_y $end
$var wire 1 $ ns_g $end
$var wire 1 % ns_r $end
$var wire 1 & ns_y $end
$var wire 1 + rst $end
$var wire 1 , tick $end
$var reg 2 - current_state [1:0] $end
$var reg 2 . next_state [1:0] $end
$var reg 3 / tick_count [2:0] $end
$upscope $end
$upscope $end
$enddefinitions $end
#0
$dumpvars
bx /
bx .
bx -
0,
1+
0*
0)
1(
0'
x&
x%
x$
x#
x"
x!
$end
#5
b0 .
0%
1"
b0 /
b0 -
1$
0&
0!
0#
1'
1*
#10
0'
0*
#15
1'
1*
#20
0'
0*
0(
0+
#25
1'
1*
#30
0'
0*
#35
1'
1*
#40
0'
0*
#45
1'
1*
#50
0'
0*
#55
1'
1*
#60
0'
0*
#65
1'
1*
#70
0'
0*
#75
1'
1*
#80
0'
0*
#85
1'
1*
#90
0'
0*
#95
1'
1*
#100
0'
0*
#105
1'
1*
#110
0'
0*
#115
1'
1*
#120
0'
0*
#125
1'
1*
#130
0'
0*
#135
1'
1*
#140
0'
0*
#145
1'
1*
#150
0'
0*
#155
1'
1*
#160
0'
0*
#165
1'
1*
#170
0'
0*
#175
1'
1*
#180
0'
0*
#185
1'
1*
#190
0'
0*
#195
1'
1*
#200
0'
0*
#205
1'
1*
#210
0'
0*
#215
1'
1*
#220
0'
0*
#225
1'
1*
#230
0'
0*
#235
1'
1*
#240
0'
0*
#245
1'
1*
#250
0'
0*
#255
1'
1*
#260
0'
0*
#265
1'
1*
#270
0'
0*
#275
1'
1*
#280
0'
0*
#285
1'
1*
#290
0'
0*
#295
1'
1*
#300
0'
0*
#305
1'
1*
#310
0'
0*
#315
1'
1*
#320
0'
0*
#325
1'
1*
#330
0'
0*
#335
1'
1*
#340
0'
0*
#345
1'
1*
#350
0'
0*
#355
1'
1*
#360
0'
0*
#365
1'
1*
#370
0'
0*
#375
1'
1*
#380
0'
0*
#385
1'
1*
#390
0'
0*
#395
1'
1*
#400
0'
0*
#405
1'
1*
#410
0'
0*
#415
1'
1*
#420
0'
0*
#425
1'
1*
#430
0'
0*
#435
1'
1*
#440
0'
0*
#445
1'
1*
#450
0'
0*
#455
1'
1*
#460
0'
0*
#465
1'
1*
#470
0'
0*
#475
1'
1*
#480
0'
0*
#485
1'
1*
#490
0'
0*
#495
1'
1*
#500
0'
0*
#505
1'
1*
#510
0'
0*
#515
1'
1*
#520
0'
0*
1)
1,
#525
b1 /
1'
1*
#530
0'
0*
#535
b10 /
1'
1*
#540
0'
0*
#545
b11 /
1'
1*
#550
0'
0*
#555
b1 .
b100 /
1'
1*
#560
0'
0*
#565
b101 /
b1 -
0$
1&
1'
1*
#570
0'
0*
#575
b110 /
1'
1*
#580
0'
0*
#585
b111 /
1'
1*
#590
0'
0*
#595
b0 /
1'
1*
#600
0'
0*
#605
b10 .
b1 /
1'
1*
#610
0'
0*
#615
1%
0"
b10 /
b10 -
0&
1!
1'
1*
#620
0'
0*
#625
b11 /
1'
1*
#630
0'
0*
#635
b11 .
b100 /
1'
1*
#640
0'
0*
#645
b101 /
b11 -
0!
1#
1'
1*
#650
0'
0*
#655
b110 /
1'
1*
#660
0'
0*
#665
b111 /
1'
1*
#670
0'
0*
#675
b0 /
1'
1*
#680
0'
0*
#685
b0 .
b1 /
1'
1*
#690
0'
0*
#695
0%
1"
b10 /
b0 -
1$
0#
1'
1*
#700
0'
0*
#705
b11 /
1'
1*
#710
0'
0*
#715
b1 .
b100 /
1'
1*
#720
0'
0*
#725
b101 /
b1 -
0$
1&
1'
1*
#730
0'
0*
#735
b110 /
1'
1*
#740
0'
0*
#745
b111 /
1'
1*
#750
0'
0*
#755
b0 /
1'
1*
#760
0'
0*
#765
b10 .
b1 /
1'
1*
#770
0'
0*
#775
1%
0"
b10 /
b10 -
0&
1!
1'
1*
#780
0'
0*
#785
b11 /
1'
1*
#790
0'
0*
#795
b11 .
b100 /
1'
1*
#800
0'
0*
#805
b101 /
b11 -
0!
1#
1'
1*
#810
0'
0*
#815
b110 /
1'
1*
#820
0'
0*
#825
b111 /
1'
1*
#830
0'
0*
#835
b0 /
1'
1*
#840
0'
0*
#845
b0 .
b1 /
1'
1*
#850
0'
0*
#855
0%
1"
b10 /
b0 -
1$
0#
1'
1*
#860
0'
0*
#865
b11 /
1'
1*
#870
0'
0*
#875
b1 .
b100 /
1'
1*
#880
0'
0*
#885
b101 /
b1 -
0$
1&
1'
1*
#890
0'
0*
#895
b110 /
1'
1*
#900
0'
0*
#905
b111 /
1'
1*
#910
0'
0*
#915
b0 /
1'
1*
#920
0'
0*
#925
b10 .
b1 /
1'
1*
#930
0'
0*
#935
1%
0"
b10 /
b10 -
0&
1!
1'
1*
#940
0'
0*
#945
b11 /
1'
1*
#950
0'
0*
#955
b11 .
b100 /
1'
1*
#960
0'
0*
#965
b101 /
b11 -
0!
1#
1'
1*
#970
0'
0*
#975
b110 /
1'
1*
#980
0'
0*
#985
b111 /
1'
1*
#990
0'
0*
#995
b0 /
1'
1*
#1000
0'
0*
#1005
b0 .
b1 /
1'
1*
#1010
0'
0*
#1015
0%
1"
b10 /
b0 -
1$
0#
1'
1*
#1020
0'
0*
0)
0,
