riscv_single_cycle/RVX-10_single-cycle/riscvsingle_new.sv
// riscvsingle_new.sv

// RISC-10 single-cycle processor
// Modified by Pankaj Nirmalkar
// Expect simulator to print "Simulation succeeded"
// when the value 25 (0x19) is written to address 100 (0x64)

// Implements a subset of the base integer instructions:
//    lw, sw
//    add, sub, and, or, slt, 
//    addi, andi, ori, slti
//    beq
//    jal
// Exceptions, traps, and interrupts not implemented
// little-endian memory

// 31 32-bit registers x1-x31, x0 hardwired to 0
// R-Type instructions
//   add, sub, and, or, slt
//   INSTR rd, rs1, rs2
//   Instr[31:25] = funct7 (funct7b5 & opb5 = 1 for sub, 0 for others)
//   Instr[24:20] = rs2
//   Instr[19:15] = rs1
//   Instr[14:12] = funct3
//   Instr[11:7]  = rd
//   Instr[6:0]   = opcode
// I-Type Instructions
//   lw, I-type ALU (addi, andi, ori, slti)
//   lw:         INSTR rd, imm(rs1)
//   I-type ALU: INSTR rd, rs1, imm (12-bit signed)
//   Instr[31:20] = imm[11:0]
//   Instr[24:20] = rs2
//   Instr[19:15] = rs1
//   Instr[14:12] = funct3
//   Instr[11:7]  = rd
//   Instr[6:0]   = opcode
// S-Type Instruction
//   sw rs2, imm(rs1) (store rs2 into address specified by rs1 + immm)
//   Instr[31:25] = imm[11:5] (offset[11:5])
//   Instr[24:20] = rs2 (src)
//   Instr[19:15] = rs1 (base)
//   Instr[14:12] = funct3
//   Instr[11:7]  = imm[4:0]  (offset[4:0])
//   Instr[6:0]   = opcode
// B-Type Instruction
//   beq rs1, rs2, imm (PCTarget = PC + (signed imm x 2))
//   Instr[31:25] = imm[12], imm[10:5]
//   Instr[24:20] = rs2
//   Instr[19:15] = rs1
//   Instr[14:12] = funct3
//   Instr[11:7]  = imm[4:1], imm[11]
//   Instr[6:0]   = opcode
// J-Type Instruction
//   jal rd, imm  (signed imm is multiplied by 2 and added to PC, rd = PC+4)
//   Instr[31:12] = imm[20], imm[10:1], imm[11], imm[19:12]
//   Instr[11:7]  = rd
//   Instr[6:0]   = opcode

//   Instruction  opcode    funct3    funct7
//   add          0110011   000       0000000
//   sub          0110011   000       0100000
//   and          0110011   111       0000000
//   or           0110011   110       0000000
//   slt          0110011   010       0000000
//   addi         0010011   000       immediate
//   andi         0010011   111       immediate
//   ori          0010011   110       immediate
//   slti         0010011   010       immediate
//   beq          1100011   000       immediate
//   lw	          0000011   010       immediate
//   sw           0100011   010       immediate
//   jal          1101111   immediate immediate
//
//   Following are the RVX-10 instructions implemented
//   andn         0001011   000       0000000
//   orn          0001011   001       0000000
//   xnor         0001011   010       0000000
//   min          0001011   000       0000001
//   max          0001011   001       0000001
//   minu         0001011   010       0000001
//   maxu         0001011   011       0000001
//   rol          0001011   000       0000010
//   ror          0001011   001       0000010
//   abs          0001011   000       0000011


module testbench();

  logic        clk;
  logic        reset;

  logic [31:0] WriteData, DataAdr;
  logic        MemWrite;

  // instantiate device to be tested
  top dut(clk, reset, WriteData, DataAdr, MemWrite);
  
  // initialize test
  initial
    begin
    $dumpfile("single.vcd");
    $dumpvars(0, dut); 

      reset <= 1; # 22; reset <= 0;
    end

  // generate clock to sequence tests
  always
    begin
      clk <= 1; # 5; clk <= 0; # 5;
    end

  // check results
  always @(negedge clk)
    begin
      if(MemWrite) begin
        if(DataAdr === 100 & WriteData === 25) begin
          $display("Simulation succeeded");
          $stop;
        end else if (DataAdr !== 96) begin
          $display("Simulation failed");
          $stop;
        end
      end
    end
endmodule

module top(input  logic        clk, reset, 
           output logic [31:0] WriteData, DataAdr, 
           output logic        MemWrite);

  logic [31:0] PC, Instr, ReadData;
  
  // instantiate processor and memories
  riscvsingle rvsingle(clk, reset, PC, Instr, MemWrite, DataAdr, 
                       WriteData, ReadData);
  imem imem(PC, Instr);
  dmem dmem(clk, MemWrite, DataAdr, WriteData, ReadData);
endmodule

module riscvsingle(input  logic        clk, reset,
                   output logic [31:0] PC,
                   input  logic [31:0] Instr,
                   output logic        MemWrite,
                   output logic [31:0] ALUResult, WriteData,
                   input  logic [31:0] ReadData);

  logic       ALUSrc, RegWrite, Jump, Zero;
  logic [1:0] ResultSrc, ImmSrc;
  logic [4:0] ALUControl;//Modified the bit for extra 10 instruction 

  controller c(Instr[6:0], Instr[14:12], { Instr[30], Instr[26:25] }, Zero,
               ResultSrc, MemWrite, PCSrc,
               ALUSrc, RegWrite, Jump,
               ImmSrc, ALUControl);
  datapath dp(clk, reset, ResultSrc, PCSrc,
              ALUSrc, RegWrite,
              ImmSrc, ALUControl,
              Zero, PC, Instr,
              ALUResult, WriteData, ReadData);
endmodule

module controller(input  logic [6:0] op,
                  input  logic [2:0] funct3,
                  input  logic [2:0] funct7b5b1b0,
                  input  logic       Zero,
                  output logic [1:0] ResultSrc,
                  output logic       MemWrite,
                  output logic       PCSrc, ALUSrc,
                  output logic       RegWrite, Jump,
                  output logic [1:0] ImmSrc,
                  output logic [4:0] ALUControl); //Modified the bit for extra 10 instruction

  logic [1:0] ALUOp;
  logic       Branch;

  maindec md(op, ResultSrc, MemWrite, Branch,
             ALUSrc, RegWrite, Jump, ImmSrc, ALUOp);
  aludec  ad(op[5], funct3, funct7b5b1b0, ALUOp, ALUControl);

  assign PCSrc = Branch & Zero | Jump;
endmodule

module maindec(input  logic [6:0] op,
               output logic [1:0] ResultSrc,
               output logic       MemWrite,
               output logic       Branch, ALUSrc,
               output logic       RegWrite, Jump,
               output logic [1:0] ImmSrc,
               output logic [1:0] ALUOp);

  logic [10:0] controls;

  assign {RegWrite, ImmSrc, ALUSrc, MemWrite,
          ResultSrc, Branch, ALUOp, Jump} = controls;

  always_comb
    case(op)
    // RegWrite_ImmSrc_ALUSrc_MemWrite_ResultSrc_Branch_ALUOp_Jump
      7'b0000011: controls = 11'b1_00_1_0_01_0_00_0; // lw
      7'b0100011: controls = 11'b0_01_1_1_00_0_00_0; // sw
      7'b0110011: controls = 11'b1_xx_0_0_00_0_10_0; // R-type 
      7'b1100011: controls = 11'b0_10_0_0_00_1_01_0; // beq
      7'b0010011: controls = 11'b1_00_1_0_00_0_10_0; // I-type ALU
      7'b1101111: controls = 11'b1_11_0_0_10_0_00_1; // jal
      7'b0001011: controls = 11'b1_xx_0_0_00_0_11_0; // For RV-10 
      default:    controls = 11'bx_xx_x_x_xx_x_xx_x; // non-implemented instruction
    endcase
endmodule

module aludec(input  logic       opb5,
              input  logic [2:0] funct3,
              input  logic [2:0] funct7b5b1b0,
              input  logic [1:0] ALUOp,
              output logic [4:0] ALUControl);

  logic  RtypeSub;
  assign RtypeSub = funct7b5b1b0[2] & opb5;           // TRUE for R-type subtract instruction
  assign RVX10ins =  { funct7b5b1b0[1:0], funct3 };   // A 5 bits long field to denote a particular RVX-10 instruction

  always_comb begin
    case (ALUOp)
        2'b00:    ALUControl = 5'b00000; // addition
        2'b01:    ALUControl = 5'b00001; // subtraction
        2'b10:    case (funct3) // R‑type or I‑type ALU
                      3'b000:  ALUControl = RtypeSub ? 5'b00001 : 5'b00000; // sub / add, addi
                      3'b010:  ALUControl = 5'b00101; // slt, slti
                      3'b110:  ALUControl = 5'b00011; // or, ori
                      3'b111:  ALUControl = 5'b00010; // and, andi
                      default: ALUControl = 5'b00xxx; // unknown
                  endcase
        2'b11:    case (RVX10ins)
                      5'b00000: ALUControl = 5'b10000; // ANDN
                      5'b00001: ALUControl = 5'b10001; // ORN
                      5'b00010: ALUControl = 5'b10010; // XNOR
                      5'b01000: ALUControl = 5'b10011; // MIN
                      5'b01001: ALUControl = 5'b10100; // MAX
                      5'b01010: ALUControl = 5'b10101; // MINU
                      5'b01011: ALUControl = 5'b10110; // MAXU
                      5'b10000: ALUControl = 5'b11000; // ROL
                      5'b10001: ALUControl = 5'b11001; // ROR
                      5'b11000: ALUControl = 5'b10111; // ABS
                      default:  ALUControl = 5'bxxxxx; // undefined RVX10 instruction
                  endcase
        default: ALUControl = 5'bxxxxx;  // Undefined instruction
    endcase
  end
endmodule

module datapath(input  logic        clk, reset,
                input  logic [1:0]  ResultSrc, 
                input  logic        PCSrc, ALUSrc,
                input  logic        RegWrite,
                input  logic [1:0]  ImmSrc,
                input  logic [4:0]  ALUControl,
                output logic        Zero,
                output logic [31:0] PC,
                input  logic [31:0] Instr,
                output logic [31:0] ALUResult, WriteData,
                input  logic [31:0] ReadData);

  logic [31:0] PCNext, PCPlus4, PCTarget;
  logic [31:0] ImmExt;
  logic [31:0] SrcA, SrcB;
  logic [31:0] Result;

  // next PC logic
  flopr #(32) pcreg(clk, reset, PCNext, PC); 
  adder       pcadd4(PC, 32'd4, PCPlus4);
  adder       pcaddbranch(PC, ImmExt, PCTarget);
  mux2 #(32)  pcmux(PCPlus4, PCTarget, PCSrc, PCNext);
 
  // register file logic
  regfile     rf(clk, RegWrite, Instr[19:15], Instr[24:20], 
                 Instr[11:7], Result, SrcA, WriteData);
  extend      ext(Instr[31:7], ImmSrc, ImmExt);

  // ALU logic
  mux2 #(32)  srcbmux(WriteData, ImmExt, ALUSrc, SrcB);
  alu         alu(SrcA, SrcB, ALUControl, ALUResult, Zero);
  mux3 #(32)  resultmux(ALUResult, ReadData, PCPlus4, ResultSrc, Result);
endmodule

module regfile(input  logic        clk, 
               input  logic        we3, 
               input  logic [ 4:0] a1, a2, a3, 
               input  logic [31:0] wd3, 
               output logic [31:0] rd1, rd2);

  logic [31:0] rf[31:0];



  always_ff @(posedge clk)
    if (we3) rf[a3] <= wd3;	

  assign rd1 = (a1 != 0) ? rf[a1] : 0;
  assign rd2 = (a2 != 0) ? rf[a2] : 0;
endmodule

module adder(input  [31:0] a, b,
             output [31:0] y);

  assign y = a + b;
endmodule

module extend(
  input  logic [31:7] instr,
  input  logic [1:0]  immsrc,
  output logic [31:0] immext
);

  logic [31:0] imm_i;
  logic [31:0] imm_s;
  logic [31:0] imm_b;
  logic [31:0] imm_j;

  // construct immediates with explicit bit widths
  assign imm_i = {{20{instr[31]}}, instr[31:20]};                             // I-type
  assign imm_s = {{20{instr[31]}}, instr[31:25], instr[11:7]};               // S-type
  assign imm_b = {{19{instr[31]}}, instr[31], instr[7], instr[30:25], instr[11:8], 1'b0}; // B-type
  // Note: B-type sign replicate 19 bits because imm field is 12 bits (bits [12]=instr[31], [11]=instr[7], [10:5]=instr[30:25], [4:1]=instr[11:8], [0]=0) -> total 13 bits, so 32-13 = 19
  assign imm_j = {{11{instr[31]}}, instr[31], instr[19:12], instr[20], instr[30:21], 1'b0}; // J-type
  // Note: J-type immediate is 21 bits (including sign), so replicate 11 bits to reach 32.

  always_comb begin
    
    case (immsrc)
      2'b00: immext = imm_i;
      2'b01: immext = imm_s;
      2'b10: immext = imm_b;
      2'b11: immext = imm_j;
      default: immext = 32'bx;
    endcase
  end

endmodule


module flopr #(parameter WIDTH = 8)
              (input  logic             clk, reset,
               input  logic [WIDTH-1:0] d, 
               output logic [WIDTH-1:0] q);

  always_ff @(posedge clk, posedge reset)
    if (reset) q <= 0;
    else       q <= d;
endmodule

module mux2 #(parameter WIDTH = 8)
             (input  logic [WIDTH-1:0] d0, d1, 
              input  logic             s, 
              output logic [WIDTH-1:0] y);

  assign y = s ? d1 : d0; 
endmodule

module mux3 #(parameter WIDTH = 8)
             (input  logic [WIDTH-1:0] d0, d1, d2,
              input  logic [1:0]       s, 
              output logic [WIDTH-1:0] y);

  assign y = s[1] ? d2 : (s[0] ? d1 : d0); 
endmodule

module imem(input  logic [31:0] a,
            output logic [31:0] rd);

  logic [31:0] RAM[63:0];  // explicitly define ascending order

  initial
      $readmemh("riscvtest.txt",RAM);

  assign rd = RAM[a[31:2]]; // word aligned
endmodule

module dmem(input  logic        clk, we,
            input  logic [31:0] a, wd,
            output logic [31:0] rd);

  logic [31:0] RAM[63:0];

  assign rd = RAM[a[31:2]]; // word aligned

  always_ff @(posedge clk)
    if (we) RAM[a[31:2]] <= wd;
endmodule

module alu(input  logic [31:0] a, b,
           input  logic [4:0]  alucontrol,
           output logic [31:0] result,
           output logic        zero);

  logic [31:0] condinvb, sum;
  logic        v;              // overflow
  logic        isAddSub;       // true when is add or subtract operation

  assign condinvb = alucontrol[0] ? ~b : b;
  assign sum = a + condinvb + alucontrol[0];
  assign isAddSub = ~alucontrol[2] & ~alucontrol[1] |
                    ~alucontrol[1] & alucontrol[0];
  assign ua = $unsigned(a);         // for unsigned instructions
  assign ub = $unsigned(b);         // for unsigned instructions
  assign shift_amount = b[4:0];     // for shift instructions
  assign slt_sign_bit = sum[31];    // for shift instructions

  // For rol (Rotate Left):
  assign a_low_31_rol = a[30:0];    // Part-select
  assign a_high_1_rol = a[31];      // Bit-select

  // For ror (Rotate Right):
  assign a_low_1_ror = a[0];        // Bit-select
  assign a_high_31_ror = a[31:1];   // Part-select

  // For abs (Absolute Value):
  assign a_sign_bit = a[31];        // Bit-select

  always_comb
    case (alucontrol)
      5'b10000: result =  a & ~b;                                                       //   ANDN
      5'b10001: result =  a | ~b;                                                       //   ORN 
      5'b10010: result =  ~(a ^ b);                                                     //   XNORN
      5'b10011: result =  (a < b) ? a : b;                                              //   MIN 
      5'b10100: result =  (a > b) ? a : b;                                              //   MAX
      5'b10101: result =  (ua < ub) ? a : b;                                            //   MINU
      5'b10110: result =  (ua > ub) ? a : b;                                            //   MAXU
      5'b11000: result = (shift_amount == 0) ? a : {a_low_31_rol, a_high_1_rol};        // ROL
      5'b11001: result = (shift_amount == 0) ? a : {a_low_1_ror, a_high_31_ror};        // ROR
      5'b10111: result = (a == 32'h80000000) ? 32'h80000000 : (a_sign_bit ? -a : a);    // ABS 

      5'b00000:  result = sum;                  //    add
      5'b00001:  result = sum;                  //    subtract
      5'b00010:  result = a & b;                //    and
      5'b00011:  result = a | b;                //    or
      5'b00100:  result = a ^ b;                //    xor
      5'b00101:  result = slt_sign_bit ^ v;     //  slt 
      5'b00110:  result = a << shift_amount;    //  sll
      5'b00111:  result = a >> shift_amount;    //  srl
      default: result = 32'bx;
    endcase

  assign zero = (result == 32'b0);
  assign v = ~(alucontrol[0] ^ a[31] ^ b[31]) & (a[31] ^ sum[31]) & isAddSub;
  
endmodule

riscv_single_cycle/RVX-10_single-cycle/single.vcd
$date
	Wed Oct  8 22:21:31 2025
$end
$version
	Icarus Verilog
$end
$timescale
	1s
$end
$scope module testbench $end
$scope module dut $end
$var wire 1 ! clk $end
$var wire 1 " reset $end
$var wire 32 # WriteData [31:0] $end
$var wire 32 $ ReadData [31:0] $end
$var wire 32 % PC [31:0] $end
$var wire 1 & MemWrite $end
$var wire 32 ' Instr [31:0] $end
$var wire 32 ( DataAdr [31:0] $end
$scope module dmem $end
$var wire 1 ! clk $end
$var wire 32 ) rd [31:0] $end
$var wire 1 & we $end
$var wire 32 * wd [31:0] $end
$var wire 32 + a [31:0] $end
$upscope $end
$scope module imem $end
$var wire 32 , rd [31:0] $end
$var wire 32 - a [31:0] $end
$upscope $end
$scope module rvsingle $end
$var wire 32 . Instr [31:0] $end
$var wire 32 / ReadData [31:0] $end
$var wire 1 ! clk $end
$var wire 1 " reset $end
$var wire 1 0 Zero $end
$var wire 32 1 WriteData [31:0] $end
$var wire 2 2 ResultSrc [1:0] $end
$var wire 1 3 RegWrite $end
$var wire 1 4 PCSrc $end
$var wire 32 5 PC [31:0] $end
$var wire 1 & MemWrite $end
$var wire 1 6 Jump $end
$var wire 2 7 ImmSrc [1:0] $end
$var wire 1 8 ALUSrc $end
$var wire 32 9 ALUResult [31:0] $end
$var wire 5 : ALUControl [4:0] $end
$scope module c $end
$var wire 1 4 PCSrc $end
$var wire 3 ; funct3 [2:0] $end
$var wire 3 < funct7b5b1b0 [2:0] $end
$var wire 7 = op [6:0] $end
$var wire 1 0 Zero $end
$var wire 2 > ResultSrc [1:0] $end
$var wire 1 3 RegWrite $end
$var wire 1 & MemWrite $end
$var wire 1 6 Jump $end
$var wire 2 ? ImmSrc [1:0] $end
$var wire 1 @ Branch $end
$var wire 1 8 ALUSrc $end
$var wire 2 A ALUOp [1:0] $end
$var wire 5 B ALUControl [4:0] $end
$scope module ad $end
$var wire 1 C RtypeSub $end
$var wire 3 D funct3 [2:0] $end
$var wire 3 E funct7b5b1b0 [2:0] $end
$var wire 1 F opb5 $end
$var wire 1 G RVX10ins $end
$var wire 2 H ALUOp [1:0] $end
$var reg 5 I ALUControl [4:0] $end
$upscope $end
$scope module md $end
$var wire 7 J op [6:0] $end
$var wire 2 K ResultSrc [1:0] $end
$var wire 1 3 RegWrite $end
$var wire 1 & MemWrite $end
$var wire 1 6 Jump $end
$var wire 2 L ImmSrc [1:0] $end
$var wire 1 @ Branch $end
$var wire 1 8 ALUSrc $end
$var wire 2 M ALUOp [1:0] $end
$var reg 11 N controls [10:0] $end
$upscope $end
$upscope $end
$scope module dp $end
$var wire 5 O ALUControl [4:0] $end
$var wire 1 8 ALUSrc $end
$var wire 2 P ImmSrc [1:0] $end
$var wire 32 Q Instr [31:0] $end
$var wire 1 4 PCSrc $end
$var wire 32 R ReadData [31:0] $end
$var wire 1 3 RegWrite $end
$var wire 2 S ResultSrc [1:0] $end
$var wire 1 ! clk $end
$var wire 1 " reset $end
$var wire 1 0 Zero $end
$var wire 32 T WriteData [31:0] $end
$var wire 32 U SrcB [31:0] $end
$var wire 32 V SrcA [31:0] $end
$var wire 32 W Result [31:0] $end
$var wire 32 X PCTarget [31:0] $end
$var wire 32 Y PCPlus4 [31:0] $end
$var wire 32 Z PCNext [31:0] $end
$var wire 32 [ PC [31:0] $end
$var wire 32 \ ImmExt [31:0] $end
$var wire 32 ] ALUResult [31:0] $end
$scope module alu $end
$var wire 5 ^ alucontrol [4:0] $end
$var wire 1 _ isAddSub $end
$var wire 1 ` v $end
$var wire 1 0 zero $end
$var wire 1 a ub $end
$var wire 1 b ua $end
$var wire 32 c sum [31:0] $end
$var wire 1 d slt_sign_bit $end
$var wire 1 e shift_amount $end
$var wire 32 f condinvb [31:0] $end
$var wire 32 g b [31:0] $end
$var wire 1 h a_sign_bit $end
$var wire 1 i a_low_31_rol $end
$var wire 1 j a_low_1_ror $end
$var wire 1 k a_high_31_ror $end
$var wire 1 l a_high_1_rol $end
$var wire 32 m a [31:0] $end
$var reg 32 n result [31:0] $end
$upscope $end
$scope module ext $end
$var wire 2 o immsrc [1:0] $end
$var wire 25 p instr [31:7] $end
$var wire 32 q imm_s [31:0] $end
$var wire 32 r imm_j [31:0] $end
$var wire 32 s imm_i [31:0] $end
$var wire 32 t imm_b [31:0] $end
$var reg 32 u immext [31:0] $end
$upscope $end
$scope module pcadd4 $end
$var wire 32 v b [31:0] $end
$var wire 32 w y [31:0] $end
$var wire 32 x a [31:0] $end
$upscope $end
$scope module pcaddbranch $end
$var wire 32 y b [31:0] $end
$var wire 32 z y [31:0] $end
$var wire 32 { a [31:0] $end
$upscope $end
$scope module pcmux $end
$var wire 32 | d0 [31:0] $end
$var wire 32 } d1 [31:0] $end
$var wire 1 4 s $end
$var wire 32 ~ y [31:0] $end
$var parameter 32 !" WIDTH $end
$upscope $end
$scope module pcreg $end
$var wire 1 ! clk $end
$var wire 32 "" d [31:0] $end
$var wire 1 " reset $end
$var parameter 32 #" WIDTH $end
$var reg 32 $" q [31:0] $end
$upscope $end
$scope module resultmux $end
$var wire 32 %" d0 [31:0] $end
$var wire 32 &" d1 [31:0] $end
$var wire 32 '" d2 [31:0] $end
$var wire 2 (" s [1:0] $end
$var wire 32 )" y [31:0] $end
$var parameter 32 *" WIDTH $end
$upscope $end
$scope module rf $end
$var wire 5 +" a1 [4:0] $end
$var wire 5 ," a2 [4:0] $end
$var wire 5 -" a3 [4:0] $end
$var wire 1 ! clk $end
$var wire 32 ." wd3 [31:0] $end
$var wire 1 3 we3 $end
$var wire 32 /" rd2 [31:0] $end
$var wire 32 0" rd1 [31:0] $end
$upscope $end
$scope module srcbmux $end
$var wire 32 1" d0 [31:0] $end
$var wire 32 2" d1 [31:0] $end
$var wire 1 8 s $end
$var wire 32 3" y [31:0] $end
$var parameter 32 4" WIDTH $end
$upscope $end
$upscope $end
$upscope $end
$upscope $end
$upscope $end
$enddefinitions $end
$comment Show the parameter values. $end
$dumpall
b100000 4"
b100000 *"
b100000 #"
b100000 !"
$end
#0
$dumpvars
b101 3"
b101 2"
bx 1"
b0 0"
bx /"
b101 ."
b10 -"
b101 ,"
b0 +"
b101 )"
b0 ("
b100 '"
bx &"
b101 %"
b0 $"
b100 ""
b100 ~
b101 }
b100 |
b0 {
b101 z
b101 y
b0 x
b100 w
b100 v
b101 u
b10 t
b101 s
b100000000100 r
b10 q
b1010000000000010 p
b0 o
b101 n
b0 m
0l
0k
0j
0i
0h
b101 g
b101 f
1e
0d
b101 c
0b
1a
0`
1_
b0 ^
b101 ]
b101 \
b0 [
b100 Z
b100 Y
b101 X
b101 W
b0 V
b101 U
bx T
b0 S
bx R
b10100000000000100010011 Q
b0 P
b0 O
b10010000100 N
b10 M
b0 L
b0 K
b10011 J
b0 I
b10 H
0G
0F
b0 E
b0 D
0C
b0 B
b10 A
0@
b0 ?
b0 >
b10011 =
b0 <
b0 ;
b0 :
b101 9
18
b0 7
06
b0 5
04
13
b0 2
bx 1
00
bx /
b10100000000000100010011 .
b0 -
b10100000000000100010011 ,
b101 +
bx *
bx )
b101 (
b10100000000000100010011 '
0&
b0 %
bx $
bx #
1"
1!
$end
#5
0!
#10
1!
#15
0!
#20
1!
#22
0"
#25
0!
#30
b1100 W
b1100 )"
b1100 ."
0e
b1100 (
b1100 +
b1100 9
b1100 ]
b1100 n
b1100 %"
0a
b1100 c
b1100 f
b1100 U
b1100 g
b1100 3"
b1100 \
b1100 u
b1100 y
b1100 2"
b1100 s
b11 q
b100000000010 t
b1100 r
b1100 ,"
b11 -"
b11000000000000011 p
b1000 Z
b1000 ~
b1000 ""
b110000000000000110010011 '
b110000000000000110010011 ,
b110000000000000110010011 .
b110000000000000110010011 Q
b10000 X
b10000 z
b10000 }
b1000 Y
b1000 w
b1000 |
b1000 '"
b100 %
b100 -
b100 5
b100 [
b100 x
b100 {
b100 $"
1!
#35
0!
#40
1e
b11 W
b11 )"
b11 ."
1a
b11111111111111111111111111110111 f
b11111111111111111111111111110111 U
b11111111111111111111111111110111 g
b11111111111111111111111111110111 3"
b11 (
b11 +
b11 9
b11 ]
b11 n
b11 %"
b11111111111111111111111111110111 \
b11111111111111111111111111110111 u
b11111111111111111111111111110111 y
b11111111111111111111111111110111 2"
b11 c
b1100 V
b1100 m
b1100 0"
b11111111111111111111111111110111 s
b11111111111111111111111111100111 q
b11111111111111111111111111100110 t
b11111111111100011000111111110110 r
b111 <
b111 E
b11 +"
b10111 ,"
b111 -"
b1111111101110001100000111 p
b1100 Z
b1100 ~
b1100 ""
b11111111011100011000001110010011 '
b11111111011100011000001110010011 ,
b11111111011100011000001110010011 .
b11111111011100011000001110010011 Q
b11111111111111111111111111111111 X
b11111111111111111111111111111111 z
b11111111111111111111111111111111 }
b1100 Y
b1100 w
b1100 |
b1100 '"
b1000 %
b1000 -
b1000 5
b1000 [
b1000 x
b1000 {
b1000 $"
1!
#45
0!
#50
0_
b111 W
b111 )"
b111 ."
b11111111111111111111111111111010 f
1k
1i
b101 U
b101 g
b101 3"
bx 7
bx ?
bx L
bx P
bx o
08
1j
1b
1d
b111 (
b111 +
b111 9
b111 ]
b111 n
b111 %"
bx \
bx u
bx y
bx 2"
1F
b1xx00000100 N
b11 :
b11 B
b11 I
b11 O
b11 ^
b11111111111111111111111111111110 c
b11 V
b11 m
b11 0"
b101 #
b101 *
b101 1
b101 T
b101 /"
b101 1"
b10 s
b100 q
b100 t
b111110000000000010 r
b110011 =
b110011 J
b110 ;
b110 D
b0 <
b0 E
b111 +"
b10 ,"
b100 -"
b100011111000100 p
b10000 Z
b10000 ~
b10000 ""
b1000111110001000110011 '
b1000111110001000110011 ,
b1000111110001000110011 .
b1000111110001000110011 Q
bx X
bx z
bx }
b10000 Y
b10000 w
b10000 |
b10000 '"
b1100 %
b1100 -
b1100 5
b1100 [
b1100 x
b1100 {
b1100 $"
1!
#55
0!
#60
b100 W
b100 )"
b100 ."
b111 f
0k
0i
0j
0b
0d
b100 (
b100 +
b100 9
b100 ]
b100 n
b100 %"
b111 U
b111 g
b111 3"
b10 :
b10 B
b10 I
b10 O
b10 ^
1G
b10011 c
b1100 V
b1100 m
b1100 0"
b111 #
b111 *
b111 1
b111 T
b111 /"
b111 1"
b100 s
b101 q
b100000000100 t
b11111000000000100 r
b111 ;
b111 D
b11 +"
b100 ,"
b101 -"
b1000001111100101 p
b10100 Z
b10100 ~
b10100 ""
b10000011111001010110011 '
b10000011111001010110011 ,
b10000011111001010110011 .
b10000011111001010110011 Q
b10100 Y
b10100 w
b10100 |
b10100 '"
b10000 %
b10000 -
b10000 5
b10000 [
b10000 x
b10000 {
b10000 $"
1!
#65
0!
#70
1_
b1011 W
b1011 )"
b1011 ."
b1011 (
b1011 +
b1011 9
b1011 ]
b1011 n
b1011 %"
b0 :
b0 B
b0 I
b0 O
b0 ^
0G
b1011 c
b100 V
b100 m
b100 0"
b101000000000000100 r
b0 ;
b0 D
b101 +"
b1000010100000101 p
b11000 Z
b11000 ~
b11000 ""
b10000101000001010110011 '
b10000101000001010110011 ,
b10000101000001010110011 .
b10000101000001010110011 Q
b11000 Y
b11000 w
b11000 |
b11000 '"
b10100 %
b10100 -
b10100 5
b10100 [
b10100 x
b10100 {
b10100 $"
1!
#75
0!
#80
b1001000 X
b1001000 z
b1001000 }
b110000 \
b110000 u
b110000 y
b110000 2"
b1 :
b1 B
b1 I
b1 O
b1 ^
b11111111111111111111111111111100 f
b1000 W
b1000 )"
b1000 ."
03
b10 7
b10 ?
b10 L
b10 P
b10 o
1@
b1 A
b1 H
b1 M
b11 U
b11 g
b11 3"
1k
1i
b1000001010 N
b11 #
b11 *
b11 1
b11 T
b11 /"
b11 1"
b100111 s
b110000 q
b110000 t
b101000100000100110 r
1j
1b
b1000 (
b1000 +
b1000 9
b1000 ]
b1000 n
b1000 %"
b1100011 =
b1100011 J
b1 <
b1 E
b111 ,"
b10000 -"
b1001110010100010000 p
b1000 c
b1011 V
b1011 m
b1011 0"
b11100 Z
b11100 ~
b11100 ""
b10011100101000100001100011 '
b10011100101000100001100011 ,
b10011100101000100001100011 .
b10011100101000100001100011 Q
b11100 Y
b11100 w
b11100 |
b11100 '"
b11000 %
b11000 -
b11000 5
b11000 [
b11000 x
b11000 {
b11000 $"
1!
#85
0!
#90
10
b0 W
b0 )"
b0 ."
b11111111111111111111111111111000 f
b101 :
b101 B
b101 I
b101 O
b101 ^
0k
0i
13
bx 7
bx ?
bx L
bx P
bx o
0@
b10 A
b10 H
b10 M
0j
0b
b0 (
b0 +
b0 9
b0 ]
b0 n
b0 %"
b111 U
b111 g
b111 3"
bx \
bx u
bx y
bx 2"
b1xx00000100 N
b101 c
b1100 V
b1100 m
b1100 0"
b111 #
b111 *
b111 1
b111 T
b111 /"
b111 1"
b100 s
b100 q
b100 t
b11010000000000100 r
b110011 =
b110011 J
b10 ;
b10 D
b0 <
b0 E
b11 +"
b100 ,"
b100 -"
b1000001101000100 p
b100000 Z
b100000 ~
b100000 ""
b10000011010001000110011 '
b10000011010001000110011 ,
b10000011010001000110011 .
b10000011010001000110011 Q
bx X
bx z
bx }
b100000 Y
b100000 w
b100000 |
b100000 '"
b11100 %
b11100 -
b11100 5
b11100 [
b11100 x
b11100 {
b11100 $"
1!
#95
0!
#100
14
1_
b0 W
b0 )"
b0 ."
b101000 X
b101000 z
b101000 }
b1000 \
b1000 u
b1000 y
b1000 2"
0e
b11111111111111111111111111111111 f
03
b10 7
b10 ?
b10 L
b10 P
b10 o
1@
b1 A
b1 H
b1 M
0d
0a
10
b0 (
b0 +
b0 9
b0 ]
b0 n
b0 %"
b1000001010 N
b1 :
b1 B
b1 I
b1 O
b1 ^
b0 c
b0 V
b0 m
b0 0"
b0 s
b1000 q
b1000 t
b100000000000000000 r
b0 U
b0 g
b0 3"
b1100011 =
b1100011 J
b0 ;
b0 D
b100 +"
b0 ,"
b1000 -"
b10000001000 p
b0 #
b0 *
b0 1
b0 T
b0 /"
b0 1"
b101000 Z
b101000 ~
b101000 ""
b100000010001100011 '
b100000010001100011 ,
b100000010001100011 .
b100000010001100011 Q
b100100 Y
b100100 w
b100100 |
b100100 '"
b100000 %
b100000 -
b100000 5
b100000 [
b100000 x
b100000 {
b100000 $"
1!
#105
0!
#110
1d
04
b1 W
b1 )"
b1 ."
1e
b11111111111111111111111111111010 f
b101 :
b101 B
b101 I
b101 O
b101 ^
1k
1i
1a
13
bx 7
bx ?
bx L
bx P
bx o
0@
b10 A
b10 H
b10 M
1j
1b
00
b1 (
b1 +
b1 9
b1 ]
b1 n
b1 %"
b101 U
b101 g
b101 3"
bx \
bx u
bx y
bx 2"
b1xx00000100 N
b11111111111111111111111111111110 c
b11 V
b11 m
b11 0"
b101 #
b101 *
b101 1
b101 T
b101 /"
b101 1"
b10 s
b100 q
b100 t
b111010000000000010 r
b110011 =
b110011 J
b10 ;
b10 D
b111 +"
b10 ,"
b100 -"
b100011101000100 p
b101100 Z
b101100 ~
b101100 ""
b1000111010001000110011 '
b1000111010001000110011 ,
b1000111010001000110011 .
b1000111010001000110011 Q
bx X
bx z
bx }
b101100 Y
b101100 w
b101100 |
b101100 '"
b101000 %
b101000 -
b101000 5
b101000 [
b101000 x
b101000 {
b101000 $"
1!
#115
0!
